[
  {
    "name": "Cameron Sampson",
    "portrait": "https://avatars0.githubusercontent.com/u/2473115?v=3&s=460",
    "presentation": {
      "title": "AR.js - Augmented Reality For the Web",
      "description": "An introduction to AR.js, an augmented reality toolkit built on top of Mozilla A-Frame that turns your camera phone into an augmented reality device!"
    },
    "social": {
      "globe": "http://cameronsampson.com",
      "github": "https://github.com/csampson"
    }
  },
  {
    "name": "Jay Casteel",
    "portrait": "https://pbs.twimg.com/profile_images/872980091663400960/eI5Mvg-Q_400x400.jpg",
    "presentation": {
      "title": "Advanced Sketch Fu",
      "description": "Do you use Sketch every day or even just wanted to learn why it’s so great? Jay will be talking about advanced Sketch techniques including powerful plugins, modular nested symbols, bulletproof resizing, animating UX prototypes with Principle, and exporting perfect Dribbble GIFs."
    },
    "social": {
      "globe": "http://jaycasteel.com", 
      "twitter": "https://twitter.com/jay_casteel"
    }
  }
]
